[{"__type__":"cc.SpriteFrame","content":{"name":"stand1","texture":"b8a4f881-e4e8-4037-b7e8-5188962e0304","rect":[0,0,666,487],"offset":[0,0],"originalSize":[666,487]}},{"__type__":"cc.SpriteFrame","content":{"name":"stand2","texture":"b8a4f881-e4e8-4037-b7e8-5188962e0304","rect":[666,0,666,487],"offset":[0,0],"originalSize":[666,487]}},{"__type__":"cc.SpriteAtlas","_name":"shenhun07.plist","_spriteFrames":{"stand1":{"__uuid__":"ce4799c8-d2e3-4225-a1c6-ce0632b3c91c"},"stand2":{"__uuid__":"3fe8f449-94f6-42d8-af05-a08cdb985c9e"},"stand3":{"__uuid__":"4bb48f81-2397-48ae-915a-3ba6bab1aae5"},"stand4":{"__uuid__":"bcd5cbed-e279-484b-9ee8-f4658088bac6"},"stand5":{"__uuid__":"5f740871-1ac4-4606-98ef-32bf205d45b6"},"stand6":{"__uuid__":"0f2e8643-c830-4d4b-8c71-69d020a2a031"},"stand7":{"__uuid__":"a547b840-2900-4046-94aa-aab7c6cc5ae9"},"stand8":{"__uuid__":"dc448b68-dae9-4018-affd-cfc79b3e8b74"}}},{"__type__":"cc.SpriteFrame","content":{"name":"stand3","texture":"b8a4f881-e4e8-4037-b7e8-5188962e0304","rect":[1332,0,666,487],"offset":[0,0],"originalSize":[666,487]}},{"__type__":"cc.SpriteFrame","content":{"name":"stand4","texture":"b8a4f881-e4e8-4037-b7e8-5188962e0304","rect":[0,487,666,487],"offset":[0,0],"originalSize":[666,487]}},{"__type__":"cc.SpriteFrame","content":{"name":"stand6","texture":"b8a4f881-e4e8-4037-b7e8-5188962e0304","rect":[1332,487,666,487],"offset":[0,0],"originalSize":[666,487]}},{"__type__":"cc.SpriteFrame","content":{"name":"stand5","texture":"b8a4f881-e4e8-4037-b7e8-5188962e0304","rect":[666,487,666,487],"offset":[0,0],"originalSize":[666,487]}},{"__type__":"cc.SpriteFrame","content":{"name":"stand7","texture":"b8a4f881-e4e8-4037-b7e8-5188962e0304","rect":[0,974,666,487],"offset":[0,0],"originalSize":[666,487]}},{"__type__":"cc.SpriteFrame","content":{"name":"stand8","texture":"b8a4f881-e4e8-4037-b7e8-5188962e0304","rect":[666,974,666,487],"offset":[0,0],"originalSize":[666,487]}}]